setup.py
flask_mongo_auth/__init__.py
flask_mongo_auth.egg-info/PKG-INFO
flask_mongo_auth.egg-info/SOURCES.txt
flask_mongo_auth.egg-info/dependency_links.txt
flask_mongo_auth.egg-info/top_level.txt