Metadata-Version: 1.0
Name: flask-mongo-auth
Version: 0.0.2
Summary: flask authentication used mongodb stored
Home-page: https://github.com/kougazhang
Author: kougazhang
Author-email: kougazhang@gmail.com
License: UNKNOWN
Platform: UNKNOWN
